igfa/__init__.py
igfa/curve_fit.py
igfa/gfa_fitflux.py
igfa/igfa_fitflux.py
igfa/model.py
igfa/plotter.py
igfa-1.0.0.2.dist-info/LICENSE
igfa-1.0.0.2.dist-info/METADATA
igfa-1.0.0.2.dist-info/WHEEL
igfa-1.0.0.2.dist-info/top_level.txt
igfa-1.0.0.2.dist-info/RECORD
